pydsb/__init__.py
pydsb-2.3.0.dist-info/METADATA
pydsb-2.3.0.dist-info/WHEEL
pydsb-2.3.0.dist-info/licenses/LICENSE
pydsb-2.3.0.dist-info/RECORD
