Metadata-Version: 2.1
Name: pydsb
Version: 2.3.0
Summary: Python API for DSBmobile
Project-URL: Homepage, https://github.com/mojansch/pydsb
Project-URL: Bug Tracker, https://github.com/mojansch/pydsb/issues
Author-email: Moritz Jannasch <contact@moritzj.de>
License-File: LICENSE
Classifier: License :: OSI Approved :: MIT License
Classifier: Operating System :: OS Independent
Classifier: Programming Language :: Python :: 3
Requires-Python: >=3.7
Requires-Dist: requests
